Workbook

Sheet Summary
G5: Consumer + Storage Device Economic Model
C6: Project Summary
C13: NPV (₪) | F13: Battery Capacity | I13: Equity IRR (%) | L13: Project IRR (%) | P13: Average Annual Gross Yield (%) | T13: Payback Period (Years)
C14: ='Tabular Data'!N92 -> 3790987.3 | F14: ='Tabular Data'!N20 -> 2280 | I14: ='Tabular Data'!N93 -> 0.65712387 | L14: ='Tabular Data'!N94 -> 0.23382336 | P14: ='Tabular Data'!N95 -> 0.22195841 | T14: ='Tabular Data'!N96 -> 3.9856839
C20: Seasonal Energy Consumption Patterns
D28: Before Storage
D30: Total Consumption (kWh) | H30: ='Tabular Data'!G39 -> 6263338
D31: Total Annual Cost (₪) | H31: ='Tabular Data'!G40 -> 3220724
H33: Consumption (kWh) | I33: Cost (₪)
D34: Peak | F34: Summer | H34: ='Tabular Data'!I43 -> 484210.12 | I34: ='Tabular Data'!J43 -> 693292.05
F35: Winter | H35: ='Tabular Data'!I44 -> 276737.84 | I35: ='Tabular Data'!J44 -> 283102.81
F36: Transitional Seasons | H36: ='Tabular Data'!I45 -> 373843.08 | I36: ='Tabular Data'!J45 -> 157687.01
D38: Low | F38: Summer | H38: ='Tabular Data'!I47 -> 1999715 | I38: ='Tabular Data'!J47 -> 895272.41
F39: Winter | H39: ='Tabular Data'!I48 -> 1057466.7 | I39: ='Tabular Data'!J48 -> 408393.65
F40: Transitional Seasons | H40: ='Tabular Data'!I49 -> 2071365.2 | I40: ='Tabular Data'!J49 -> 782976.06
D43: With Storage
D45: Total Consumption (kWh) | H45: ='Tabular Data'!Q39 -> 6302803.6
D46: Total Annual Cost (₪) | H46: ='Tabular Data'!Q40 -> 2948624.9
H48: Consumption (kWh) | I48: Cost (₪)
D49: Peak | F49: Summer | H49: ='Tabular Data'!S43 -> 304588.08 | I49: ='Tabular Data'!T43 -> 436109.21 | J49: Description
F50: Winter | H50: ='Tabular Data'!S44 -> 101169.17 | I50: ='Tabular Data'!T44 -> 103496.06
F51: Transitional Seasons | H51: ='Tabular Data'!S45 -> 373843.08 | I51: ='Tabular Data'!T45 -> 157687.01 | J51: This chart illustrates the daily energy consumption during low and peak hours across different seasons: winter, summer, and transitional seasons. The histograms compare energy usage levels. The x-axis represents daily energy consumption in kilowatt-hours (kWh), while the y-axis indicates the frequency of days each consumption level is observed. This visualization aids in understanding the variations in energy consumption across seasons and time periods.
D53: Low | F53: Summer | H53: ='Tabular Data'!S47 -> 2199295 | I53: ='Tabular Data'!T47 -> 984624.39
F54: Winter | H54: ='Tabular Data'!S48 -> 1252543 | I54: ='Tabular Data'!T48 -> 483732.11
F55: Transitional Seasons | H55: ='Tabular Data'!S49 -> 2071365.2 | I55: ='Tabular Data'!T49 -> 782976.06
C58: Optimal Storage Size
L65: Description | R65: Parameters
L67: ="his graph shows how the Project Internal Rate of Return (PIRR) changes with the size of the storage device (battery capacity). The x-axis represents the battery capacity in kilowatt-hours (kWh), and the y-axis shows the Project IRR." & "The optimal storage capacity, which maximizes the Project IRR, is " & 'Tabular Data'!D57 & " kWh." -> his graph shows how the Project Internal Rate of Return (PIRR) changes with the size of the storage device (battery capacity). The x-axis represents the battery capacity in kilowatt-hours (kWh), and the y-axis shows the Project IRR.The optimal storage capacity, which maximizes the Project IRR, is kWh. | R67: Global Constants | T67: Exchange Rate (₪/$) | W67: ='Tabular Data'!I11 -> 3.7
T68: Inflation Rate | W68: ='Tabular Data'!I12 -> 0.06
T69: Prime Interest Rate | W69: ='Tabular Data'!I13 -> 0.06
T70: Discount Rate | W70: ='Tabular Data'!I14 -> 0.05
R72: Financing Details | T72: Marginal Annual Interest Rate | W72: =Summary!S11 -> 0
T73: Marginal Annual Interest Rate Growth | W73: =Summary!S12 -> 0
T74: Repayment Period (Years) | W74: =Summary!S13 -> 0
T75: Own Funds Ratio | W75: =Summary!S14 -> 0
T76: Voltage Type | W76: ='Tabular Data'!S15 -> Low Voltage General Consumer IEC
R78: Capital Expenditure (Capex) | T78: Initial Capex (₪) | W78: ='Tabular Data'!N26 -> 0
T79: Annual Opex (₪) | W79: ='Tabular Data'!N27 -> 0
R81: Additional Specifications | T81: Response Time Window (hr) | W81: ='Tabular Data'!N19 -> <0.5
T82: Battery Cost per kWh ($) | W82: ='Tabular Data'!N18 -> 230
C88: ="Optimal Use of Storage With Capacity of " & TEXT('Tabular Data'!N20, 0) & " kWh " -> Optimal Use of Storage With Capacity of 2280 kWh
F98: Description
F100: Daily energy consumption during peak hours, comparing scenarios with and without a storage device. The orange line represents energy consumption without the storage device, while the green line illustrates consumption with the storage device. The graph is segmented into three seasons: winter, transitional seasons, and summer. Notably, during the transitional seasons, peak energy consumption is the same for both scenarios, reflecting zero arbitrage in these periods.
P131: Description
P133: This graph shows the percentage of battery usage by date, with the orange line indicating load shedding events in 2022 and the green line representing events in 2023. The transitional seasons are highlighted as the optimal times for participating in load shedding events, as battery usage is minimal during these periods.
C158: Cash Flow
D165: Description
D167: This graph provides an overview of the annual cash flow for a storage project, detailing revenue sources and costs. The bars are color-coded: varying shades of green for revenues and red for costs, including operational expenses, loan repayments, and interest. The initial investment is highlighted at the start, and the net cash flow throughout the project’s lifespan is indicated by a black line.
C216: Cummulative Cash Flow
D217: Description
D219: ="This graph shows the cumulative cash flow throughout the project’s lifespan. The point at which the investment is returned is marked during the "& FLOOR('Tabular Data'!N96, 1)&IF(AND('Tabular Data'!N96>=10,'Tabular Data'!M57<=20),"th",CHOOSE(MOD('Tabular Data'!N96,10),"st","nd","rd","th","th","th","th","th","th")&" year of the project, as indicated. The graph highlights how cash flow accumulates over time, providing a clear view of when the project breaks even and begins generating profit.") -> This graph shows the cumulative cash flow throughout the project’s lifespan. The point at which the investment is returned is marked during the 3rd year of the project, as indicated. The graph highlights how cash flow accumulates over time, providing a clear view of when the project breaks even and begins generating profit.

Sheet Tabular Data
B1: Economic Model For Storage Device
K3: Contact Information | M3: גל זלוף
B8: Parameters
E10: Global Constants | O10: Financing Details
E11: Exchange Rate (₪/$) | I11: 3.7 | O11: Marginal Annual Interest Rate | S11: 0.02
E12: Inflation Rate | I12: 0.06 | O12: Marginal Annual Interest Rate Growth
E13: Prime Interest Rate | I13: 0.06 | O13: Repayment Period (Years) | S13: 10
E14: Discount Rate | I14: 0.05 | O14: Own Funds Ratio | S14: 0.2
O15: Voltage Type | S15: Low Voltage General Consumer IEC
E17: Additional Specifications
E18: Battery Cost per kWh ($) | N18: 230
E19: Response Time Window (hr) | N19: <0.5
E20: Battery Size (kWh) | N20: 2280
E21: Annual Degradation | N21: 0.02
E22: Round-Trip-Efficiency | N22: 0.9
E23: Depth-of-Discharge | N23: 1
E25: Capital Expenditure (Capex)
E26: Initial Capex (₪) | N26: 0
E27: Annual Opex (₪)
B33: Annual Consumption Data Summary
E36: Before Storage | O36: With Storage
E39: Total Consumption (kWh) | G39: 6263338 | O39: Total Consumption (kWh) | Q39: 6302803.6
E40: Total Annual Cost (₪) | G40: 3220724 | O40: Total Annual Cost (₪) | Q40: 2948624.9
I42: Consumption (kWh) | J42: Cost (₪) | S42: Consumption (kWh) | T42: Cost (₪)
E43: Peak | G43: Summer | I43: 484210.12 | J43: 693292.05 | O43: Peak | Q43: Summer | S43: 304588.08 | T43: 436109.21
G44: Winter | I44: 276737.84 | J44: 283102.81 | K44: שעות יקרות | Q44: Winter | S44: 101169.17 | T44: 103496.06
G45: Transitional Seasons | I45: 373843.08 | J45: 157687.01 | K45: =J45+J44+J43 -> 1134081.9 | L45: =U45 -> 697292.29 | M45: =L45-K45 -> -436789.58 | Q45: Transitional Seasons | S45: 373843.08 | T45: 157687.01 | U45: =SUM(T43:T45) -> 697292.29
E47: Low | G47: Summer | I47: 1999715 | J47: 895272.41 | O47: Low | Q47: Summer | S47: 2199295 | T47: 984624.39
G48: Winter | I48: 1057466.7 | J48: 408393.65 | K48: שעות זולות | Q48: Winter | S48: 1252543 | T48: 483732.11
G49: Transitional Seasons | I49: 2071365.2 | J49: 782976.06 | K49: =J49+J48+J47 -> 2086642.1 | L49: =U49 -> 2251332.6 | M49: =L49-K49 -> 164690.45 | Q49: Transitional Seasons | S49: 2071365.2 | T49: 782976.06 | U49: =SUM(T47:T49) -> 2251332.6
M50: =M49+M45 -> -272099.13
B53: Yearly Revenues Aggregation
I55: Total number of cycles per year | K55: Battery Cost (₪) | M55: Project Cost (₪) | O55: Equity (₪)
I56: 176 | K56: 1940280 | M56: 1940280 | O56: 388056
E58: חיסכון תעו״ז | F58: מכירה
D59: Year | E59: Revenue (₪) | H59: Expenses | M59: Project Cash Flow | O59: Financing | S59: Free Cash Flow | U59: Gross Yield on Equity
E61: Load Shifting | F61: Load Shedding | G61: Total Revenue | H61: Management Fees | I61: Insurance | J61: o&m | K61: Unexpected Costs | L61: Total Expenses | M61: Per Year | N61: Cumulative | O61: fund | P61: repayment | Q61: interest | R61: total | S61: per year | T61: cumulative
D62: 0 | E62: 0 | F62: 0 | G62: 0 | H62: 0 | I62: 0 | J62: 0 | K62: 0 | L62: 0 | M62: -1940280 | N62: -1940280 | O62: 1552224 | P62: 0 | Q62: 0 | R62: 0 | S62: -388056 | T62: -388056 | U62: 0
D63: 1 | E63: 272099.13 | F63: 251629.91 | G63: 523729.04 | H63: 15711.871 | I63: 11400 | J63: 0 | K63: 3000 | L63: 30111.871 | M63: 493617.17 | N63: -1446662.8 | O63: 1445074.8 | P63: 107149.23 | Q63: 124177.92 | R63: 231327.15 | S63: 262290.02 | T63: -125765.98 | U63: 0.25440512
D64: 2 | E64: 267342.51 | F64: 251629.91 | G64: 518972.43 | H64: 15569.173 | I64: 11400 | J64: 0 | K64: 3000 | L64: 29969.173 | M64: 489003.25 | N64: -957659.58 | O64: 1329353.6 | P64: 115721.17 | Q64: 115605.98 | R64: 231327.15 | S64: 257676.1 | T64: 131910.13 | U64: 0.25202716
D65: 3 | E65: 262681.03 | F65: 251629.91 | G65: 514310.94 | H65: 15429.328 | I65: 11400 | J65: 0 | K65: 3000 | L65: 29829.328 | M65: 484481.61 | N65: -473177.96 | O65: 1204374.7 | P65: 124978.86 | Q65: 106348.29 | R65: 231327.15 | S65: 253154.46 | T65: 385064.59 | U65: 0.24969675
D66: 4 | E66: 258112.77 | F66: 251629.91 | G66: 509742.69 | H66: 15292.281 | I66: 11400 | J66: 0 | K66: 3000 | L66: 29692.281 | M66: 480050.41 | N66: 6872.441 | O66: 1069397.6 | P66: 134977.17 | Q66: 96349.979 | R66: 231327.15 | S66: 248723.26 | T66: 633787.84 | U66: 0.24741295
D67: 5 | E67: 253635.88 | F67: 251629.91 | G67: 505265.8 | H67: 15157.974 | I67: 11400 | J67: 0 | K67: 3000 | L67: 29557.974 | M67: 475707.82 | N67: 482580.26 | O67: 923622.23 | P67: 145775.34 | Q67: 85551.806 | R67: 231327.15 | S67: 244380.67 | T67: 878168.52 | U67: 0.24517483
D68: 6 | E68: 249248.53 | F68: 251159.82 | G68: 500408.35 | H68: 15012.25 | I68: 11400 | J68: 15960 | K68: 3000 | L68: 45372.25 | M68: 455036.1 | N68: 937616.36 | O68: 766184.86 | P68: 157437.37 | Q68: 73889.778 | R68: 231327.15 | S68: 223708.95 | T68: 1101877.5 | U68: 0.23452084
D69: 7 | E69: 244948.93 | F69: 246136.62 | G69: 491085.55 | H69: 14732.566 | I69: 11400 | J69: 15960 | K69: 3000 | L69: 45092.566 | M69: 445992.98 | N69: 1383609.3 | O69: 596152.5 | P69: 170032.36 | Q69: 61294.789 | R69: 231327.15 | S69: 214665.83 | T69: 1316543.3 | U69: 0.22986011
D70: 8 | E70: 240719.23 | F70: 241213.89 | G70: 481933.12 | H70: 14457.994 | I70: 11400 | J70: 15960 | K70: 3000 | L70: 44817.994 | M70: 437115.12 | N70: 1820724.5 | O70: 412517.55 | P70: 183634.95 | Q70: 47692.2 | R70: 231327.15 | S70: 205787.97 | T70: 1522331.3 | U70: 0.22528456
D71: 9 | E71: 236567.58 | F71: 236389.61 | G71: 472957.19 | H71: 14188.716 | I71: 11400 | J71: 15960 | K71: 3000 | L71: 44548.716 | M71: 428408.48 | N71: 2249132.9 | O71: 214191.8 | P71: 198325.75 | Q71: 33001.404 | R71: 231327.15 | S71: 197081.33 | T71: 1719412.6 | U71: 0.22079725
D72: 10 | E72: 232484.54 | F72: 231661.82 | G72: 464146.36 | H72: 13924.391 | I72: 11400 | J72: 15960 | K72: 3000 | L72: 44284.391 | M72: 419861.97 | N72: 2668994.9 | O72: 1.6298145e-09 | P72: 214191.8 | Q72: 17135.344 | R72: 231327.15 | S72: 188534.82 | T72: 1907947.4 | U72: 0.21639246
D73: 11 | E73: 228463.6 | F73: 227028.58 | G73: 455492.18 | H73: 13664.766 | I73: 11400 | J73: 15960 | K73: 3000 | L73: 44024.766 | M73: 411467.42 | N73: 3080462.3 | O73: 0 | P73: 0 | Q73: 0 | R73: 0 | S73: 411467.42 | T73: 2319414.8 | U73: 0.212066
... D79: 17 | E79: 205463.03 | F79: 201111.54 | G79: 406574.57 | H79: 12197.237 | I79: 11400 | J79: 15960 | K79: 3000 | L79: 42557.237 | M79: 364017.34 | N79: 5380965 | O79: 0 | P79: 0 | Q79: 0 | R79: 0 | S79: 364017.34 | T79: 4619917.5 | U79: 0.18761072
D80: 18
D81: 19
D82: 20
D83: 21
D84: 22
D85: 23
D86: 24
D87: 25
B89: Projectile Metrics
B92: NPV (₪) | N92: 3790987.3
B93: Equity IRR (%) | N93: 0.65712387
B94: Project IRR (%) | N94: 0.23382336
B95: Average Annual Gross Yield (%) | N95: 0.22195841
B96: Payback Period (Years) | N96: 3.9856839
B99: enSights may allow the Customer to use its Production Calculator which is currently under development and should be considered as beta version. The Production Calculator shall be deemed an integral part of the Platform, however, it is provided “as is” with no warranties whatsoever notwithstanding anything to the contrary in this Agreement.
B100: “Production Calculator” means Company’s assisting tool for the sizing of BESS deployment.
